azure/__init__.py
azure/cli/__init__.py
azure/cli/command_modules/__init__.py
azure/cli/command_modules/advisor/__init__.py
azure/cli/command_modules/advisor/_client_factory.py
azure/cli/command_modules/advisor/_help.py
azure/cli/command_modules/advisor/_params.py
azure/cli/command_modules/advisor/_validators.py
azure/cli/command_modules/advisor/commands.py
azure/cli/command_modules/advisor/custom.py
azure_cli_advisor-2.0.1.dist-info/METADATA
azure_cli_advisor-2.0.1.dist-info/WHEEL
azure_cli_advisor-2.0.1.dist-info/top_level.txt
azure_cli_advisor-2.0.1.dist-info/RECORD
